[
  {
    "type": "function",
    "function": {
      "name": "hera_describe_device",
      "description": "Create a detailed description of the requested device.",
      "parameters": {
        "type": "object",
        "properties": {
          "device": {
            "type": "string",
            "description": "human-readable device name, unique per HERA."
          }
        },
        "required": [
          "device"
        ]
      }
    }
  },
  {
    "type": "function",
    "function": {
      "name": "hera_get_device_actions",
      "description": "Retrieves the actions supported by a device.",
      "parameters": {
        "type": "object",
        "properties": {
          "device": {
            "type": "string",
            "description": "human-readable device name, unique per HERA."
          }
        },
        "required": [
          "device"
        ]
      }
    }
  },
  {
    "type": "function",
    "function": {
      "name": "hera_get_heating_state",
      "description": "Get central heating state.",
      "parameters": {
        "type": "object",
        "properties": {}
      }
    }
  },
  {
    "type": "function",
    "function": {
      "name": "hera_list_devices",
      "description": "List all devices registered to HERA.",
      "parameters": {
        "type": "object",
        "properties": {}
      }
    }
  },
  {
    "type": "function",
    "function": {
      "name": "hera_read_humidity",
      "description": "Read current humidity.",
      "parameters": {
        "type": "object",
        "properties": {}
      }
    }
  },
  {
    "type": "function",
    "function": {
      "name": "hera_read_sensors",
      "description": "Read all registered sensors.",
      "parameters": {
        "type": "object",
        "properties": {}
      }
    }
  },
  {
    "type": "function",
    "function": {
      "name": "hera_read_temperature",
      "description": "Read the current temperature from devices in a specified zone.",
      "parameters": {
        "type": "object",
        "properties": {
          "zone": {
            "type": "string",
            "description": "human-readable zone name of the location where the devices are placed."
          }
        },
        "required": [
          "zone"
        ]
      }
    }
  },
  {
    "type": "function",
    "function": {
      "name": "hera_run_diagnose",
      "description": "Check that a device is reachable and running properly. Return a diagnosis report.",
      "parameters": {
        "type": "object",
        "properties": {
          "device": {
            "type": "string",
            "description": "human-readable device name, unique per HERA."
          }
        },
        "required": [
          "device"
        ]
      }
    }
  },
  {
    "type": "function",
    "function": {
      "name": "hera_start_heating",
      "description": "Start central heating.",
      "parameters": {
        "type": "object",
        "properties": {}
      }
    }
  },
  {
    "type": "function",
    "function": {
      "name": "hera_stop_heating",
      "description": "Stop central heating.",
      "parameters": {
        "type": "object",
        "properties": {}
      }
    }
  }
]